collective.themefragments-2.11.1-py2.7-nspkg.pth
collective/themefragments/__init__.py
collective/themefragments/configure.zcml
collective/themefragments/interfaces.py
collective/themefragments/testing.py
collective/themefragments/tiles.py
collective/themefragments/traversal.py
collective/themefragments/utils.py
collective/themefragments/profiles/default/metadata.xml
collective/themefragments/profiles/default/registry.xml
collective/themefragments/tests/__init__.py
collective/themefragments/tests/configure.zcml
collective/themefragments/tests/test_traversal.py
collective/themefragments/tests/resources/fragment.xml
collective/themefragments/tests/resources/index.html
collective/themefragments/tests/resources/manifest.cfg
collective/themefragments/tests/resources/rules.xml
collective/themefragments/tests/resources/theme.html
collective/themefragments/tests/resources/fragments/customnav.pt
collective/themefragments/tests/resources/fragments/document_view.pt
collective/themefragments/tests/resources/fragments/document_view.py
collective/themefragments/tests/resources/fragments/invalid.pt
collective/themefragments/tests/resources/fragments/scripted_customnav.pt
collective/themefragments/tests/resources/fragments/scripted_customnav.title.py
collective/themefragments/tests/resources/fragments/scripted_customnav_module.pt
collective/themefragments/tests/resources/fragments/scripted_customnav_module.py
collective/themefragments/tests/resources/fragments/scripted_invalid.owner.py
collective/themefragments/tests/resources/fragments/scripted_invalid.pt
collective/themefragments/tests/resources/fragments/scripted_invalid_module.pt
collective/themefragments/tests/resources/fragments/scripted_invalid_module.py
collective.themefragments-2.11.1.dist-info/DESCRIPTION.rst
collective.themefragments-2.11.1.dist-info/METADATA
collective.themefragments-2.11.1.dist-info/RECORD
collective.themefragments-2.11.1.dist-info/WHEEL
collective.themefragments-2.11.1.dist-info/entry_points.txt
collective.themefragments-2.11.1.dist-info/metadata.json
collective.themefragments-2.11.1.dist-info/namespace_packages.txt
collective.themefragments-2.11.1.dist-info/top_level.txt
