Metadata-Version: 2.0
Name: collective.themefragments
Version: 2.11.1
Summary: Theme fragments for plone.app.theming
Home-page: https://github.com/collective/collective.themefragments/
Author: Asko Soukka
Author-email: asko.soukka@iki.fi
License: GPL
Platform: UNKNOWN
Classifier: Programming Language :: Python
Classifier: Framework :: Plone :: 4.1
Classifier: Framework :: Plone :: 4.2
Classifier: Framework :: Plone :: 4.3
Requires-Dist: plone.app.theming
Requires-Dist: setuptools
Provides-Extra: test
Requires-Dist: plone.app.testing; extra == 'test'
Requires-Dist: plone.app.textfield; extra == 'test'
